[
  {
    "AppUserId": 10,
    "ArtworkId": 5,
    "BuyDate": "1970-11-23",
    "BuyPrice": 2692
  },
  
  {
    "AppUserId": 1,
    "ArtworkId": 1,
    "BuyDate": "1970-10-11",
    "BuyPrice": 8891
  },
  
  {
    "AppUserId": 9,
    "ArtworkId": 9,
    "BuyDate": "1970-04-25",
    "BuyPrice": 8586
  },
  
  {
    "AppUserId": 1,
    "ArtworkId": 3,
    "BuyDate": "1970-09-09",
    "BuyPrice": 1718
  },
  
  {
    "AppUserId": 2,
    "ArtworkId": 7,
    "BuyDate": "1970-03-22",
    "BuyPrice": 4276
  },
  
  {
    "AppUserId": 6,
    "ArtworkId": 4,
    "BuyDate": "1970-06-17",
    "BuyPrice": 6164
  },
  
  {
    "AppUserId": 7,
    "ArtworkId": 1,
    "BuyDate": "1970-04-25",
    "BuyPrice": 8910
  },
  
  {
    "AppUserId": 2,
    "ArtworkId": 5,
    "BuyDate": "1970-01-25",
    "BuyPrice": 9349
  },
  
  {
    "AppUserId": 4,
    "ArtworkId": 1,
    "BuyDate": "1970-12-25",
    "BuyPrice": 6510
  },
  
  {
    "AppUserId": 8,
    "ArtworkId": 9,
    "BuyDate": "1970-03-22",
    "BuyPrice": 9873
  }
]
